{
	"file_path": "C:\\Users\\Sofia\\AppData\\Local\\Packages\\Microsoft.MinecraftUWP_8wekyb3d8bbwe\\LocalState\\games\\com.mojang\\development_behavior_packs\\Ender Elevators BP\\recipes\\MK5\\ORANGE\\orange_elevator_omni_mk1_color.json",
	"file_type": "recipe",
	"format_version": 1,
	"file_uuid": "67574c80_9f8d_4e32_92bb_b4f1e5ab49d6",
	"file_version": 14,
	"cache_content": {
		"children": [
			{
				"data": "1.16.100",
				"key": "format_version"
			},
			{
				"open": {
					"format_version": "1.16.100",
					"minecraft:recipe_shapeless": {
						"description": {
							"identifier": "se:orange_elevator_omni_mk1_color"
						},
						"tags": [
							"crafting_table"
						],
						"ingredients": [
							{
								"item": "se:elevator_omni_mk1",
								"count": 1
							},
							{
								"item": "minecraft:dye",
								"data": 14,
								"count": 1
							}
						],
						"result": [
							{
								"item": "se:orange_elevator_omni_mk1",
								"count": 1
							}
						]
					}
				},
				"key": "minecraft:recipe_shapeless",
				"children": [
					{
						"open": {
							"description": {
								"identifier": "se:orange_elevator_omni_mk1_color"
							},
							"tags": [
								"crafting_table"
							],
							"ingredients": [
								{
									"item": "se:elevator_omni_mk1",
									"count": 1
								},
								{
									"item": "minecraft:dye",
									"data": 14,
									"count": 1
								}
							],
							"result": [
								{
									"item": "se:orange_elevator_omni_mk1",
									"count": 1
								}
							]
						},
						"key": "description",
						"is_minified": true,
						"children": {
							"identifier": "se:orange_elevator_omni_mk1_color"
						}
					},
					{
						"key": "tags",
						"is_minified": true,
						"children": [
							"crafting_table"
						]
					},
					{
						"open": {
							"description": {
								"identifier": "se:orange_elevator_omni_mk1_color"
							},
							"tags": [
								"crafting_table"
							],
							"ingredients": [
								{
									"item": "se:elevator_omni_mk1",
									"count": 1
								},
								{
									"item": "minecraft:dye",
									"data": 14,
									"count": 1
								}
							],
							"result": [
								{
									"item": "se:orange_elevator_omni_mk1",
									"count": 1
								}
							]
						},
						"key": "ingredients",
						"children": [
							{
								"open": [
									{
										"item": "se:elevator_omni_mk1",
										"count": 1
									},
									{
										"item": "minecraft:dye",
										"data": 14,
										"count": 1
									}
								],
								"is_minified": true,
								"children": {
									"item": "se:elevator_omni_mk1",
									"count": 1
								}
							},
							{
								"open": [
									{
										"item": "se:elevator_omni_mk1",
										"count": 1
									},
									{
										"item": "minecraft:dye",
										"data": 14,
										"count": 1
									}
								],
								"is_minified": true,
								"children": {
									"item": "minecraft:dye",
									"data": 14,
									"count": 1
								}
							}
						]
					},
					{
						"open": {
							"description": {
								"identifier": "se:orange_elevator_omni_mk1_color"
							},
							"tags": [
								"crafting_table"
							],
							"ingredients": [
								{
									"item": "se:elevator_omni_mk1",
									"count": 1
								},
								{
									"item": "minecraft:dye",
									"data": 14,
									"count": 1
								}
							],
							"result": [
								{
									"item": "se:orange_elevator_omni_mk1",
									"count": 1
								}
							]
						},
						"key": "result",
						"children": [
							{
								"open": [
									{
										"item": "se:orange_elevator_omni_mk1",
										"count": 1
									}
								],
								"is_minified": true,
								"children": {
									"item": "se:orange_elevator_omni_mk1",
									"count": 1
								}
							}
						]
					}
				]
			}
		]
	}
}