{
	"format_version": "1.12.0",
	"minecraft:geometry": [
		{
			"description": {
				"identifier": "geometry.beetle",
				"texture_width": 64,
				"texture_height": 64,
				"visible_bounds_width": 3,
				"visible_bounds_height": 1.5,
				"visible_bounds_offset": [0, 0.25, 0]
			},
			"bones": [
				{
					"name": "Torso",
					"pivot": [0, 0, 0],
					"cubes": [
						{"origin": [-6, 0, -7], "size": [12, 8, 16], "uv": [0, 16]}
					]
				},
				{
					"name": "Cabeza",
					"pivot": [0, 0, 0],
					"cubes": [
						{"origin": [-4, 2, -11], "size": [8, 4, 4], "uv": [40, 4]}
					]
				},
				{
					"name": "Cuerno",
					"parent": "Cabeza",
					"pivot": [15, 4, -16],
					"rotation": [-90, 0, 0],
					"cubes": [
						{"origin": [4, 4, -15], "size": [1, 1, 0], "uv": [32, 47]},
						{"origin": [5, 5, -15], "size": [1, 2, 0], "uv": [33, 45]},
						{"origin": [6, 6, -15], "size": [1, 2, 0], "uv": [34, 44]},
						{"origin": [6, 8, -15], "size": [1, 2, 0], "uv": [34, 42]},
						{"origin": [5, 9, -15], "size": [1, 2, 0], "uv": [33, 41]},
						{"origin": [4, 10, -15], "size": [1, 2, 0], "uv": [32, 40]}
					]
				},
				{
					"name": "Cuerno2",
					"parent": "Cabeza",
					"pivot": [-15, 1, -16],
					"rotation": [-90, 0, 175],
					"cubes": [
						{"origin": [-26, 1, -15], "size": [1, 1, 0], "uv": [32, 47]},
						{"origin": [-25, 2, -15], "size": [1, 2, 0], "uv": [33, 45]},
						{"origin": [-24, 3, -15], "size": [1, 2, 0], "uv": [34, 44]},
						{"origin": [-24, 5, -15], "size": [1, 2, 0], "uv": [34, 42]},
						{"origin": [-25, 6, -15], "size": [1, 2, 0], "uv": [33, 41]},
						{"origin": [-26, 7, -15], "size": [1, 2, 0], "uv": [32, 40]}
					]
				},
				{
					"name": "Pata1",
					"pivot": [9, 4, 5],
					"rotation": [0, 0, -180],
					"cubes": [
						{"origin": [11, 1, 6], "size": [1, 2, 0], "uv": [8, 46]},
						{"origin": [10, 2, 6], "size": [1, 2, 0], "uv": [9, 44]},
						{"origin": [9, 4, 6], "size": [1, 2, 0], "uv": [10, 42]},
						{"origin": [8, 6, 6], "size": [1, 2, 0], "uv": [11, 40]}
					]
				},
				{
					"name": "Pata2",
					"pivot": [18, 0, -9],
					"cubes": [
						{"origin": [7, 1, -4], "size": [1, 2, 0], "uv": [18, 41]},
						{"origin": [6, 2, -4], "size": [1, 2, 0], "uv": [16, 40]},
						{"origin": [8, 0, -4], "size": [1, 2, 0], "uv": [20, 42]}
					]
				},
				{
					"name": "Pata3",
					"pivot": [18, 2, 16],
					"cubes": [
						{"origin": [9, 0, 1], "size": [1, 2, 0], "uv": [47, 46]},
						{"origin": [8, 2, 1], "size": [1, 2, 0], "uv": [46, 45]},
						{"origin": [7, 3, 1], "size": [1, 2, 0], "uv": [45, 42]},
						{"origin": [6, 4, 1], "size": [1, 2, 0], "uv": [44, 40]}
					]
				},
				{
					"name": "Pata4",
					"pivot": [-9, 4, 7],
					"rotation": [0, 177.5, -180],
					"cubes": [
						{"origin": [-7, 1, 8], "size": [1, 2, 0], "uv": [8, 46]},
						{"origin": [-8, 2, 8], "size": [1, 2, 0], "uv": [9, 44]},
						{"origin": [-9, 4, 8], "size": [1, 2, 0], "uv": [10, 42]},
						{"origin": [-10, 6, 8], "size": [1, 2, 0], "uv": [11, 40]}
					]
				},
				{
					"name": "Pata5",
					"pivot": [-17, 2, -14],
					"rotation": [0, 177.5, 0],
					"cubes": [
						{"origin": [-26, 0, -29], "size": [1, 2, 0], "uv": [47, 46]},
						{"origin": [-27, 2, -29], "size": [1, 2, 0], "uv": [46, 45]},
						{"origin": [-28, 3, -29], "size": [1, 2, 0], "uv": [45, 42]},
						{"origin": [-29, 4, -29], "size": [1, 2, 0], "uv": [44, 40]}
					]
				},
				{
					"name": "Pata6",
					"pivot": [-8, 0, -5],
					"rotation": [0, 177.5, 0],
					"cubes": [
						{"origin": [-9, 1, -6], "size": [1, 2, 0], "uv": [18, 41]},
						{"origin": [-10, 2, -6], "size": [1, 2, 0], "uv": [16, 40]},
						{"origin": [-8, 0, -6], "size": [1, 2, 0], "uv": [20, 42]}
					]
				}
			]
		}
	]
}